codexctl/__init__.py
codexctl/__main__.py
codexctl/analysis.py
codexctl/device.py
codexctl/server.py
codexctl/sync.py
codexctl/updates.py
codexctl-1.1.0.dist-info/entry_points.txt
codexctl-1.1.0.dist-info/LICENSE
codexctl-1.1.0.dist-info/METADATA
codexctl-1.1.0.dist-info/WHEEL
codexctl-1.1.0.dist-info/RECORD
