Metadata-Version: 2.1
Name: codexctl
Version: 1.1.0
Summary: Automated update managment for the ReMarkable tablet
License: GPLv3
Author: Jayy001
Author-email: github@skii.dev
Requires-Python: >=3.12,<4.0
Classifier: License :: Other/Proprietary License
Classifier: Programming Language :: Python :: 3
Classifier: Programming Language :: Python :: 3.12
Requires-Dist: loguru (==0.7.2)
Requires-Dist: paramiko (==3.4.1)
Requires-Dist: psutil (==6.0.0)
Requires-Dist: remarkable-update-fuse (==1.1.2) ; sys_platform == "linux"
Requires-Dist: remarkable-update-image (==1.1.3) ; sys_platform != "linux"
Requires-Dist: requests (==2.31.0)
